{
	"format_version": "1.8.0",
	"animations": {
		"animation.walk": {
			"loop": true,
			"animation_length": 4,
			"bones": {
				"main": {
					"rotation": {
						"0.0": {
							"vector": [0, 7.5, 0]
						},
						"2.0": {
							"vector": [0, 7.5, 0]
						}
					}
				},
				"legs": {
					"rotation": {
						"0.0": {
							"vector": [0, 15, 0]
						},
						"1.0": {
							"vector": [0, -10, 0]
						},
						"2.0": {
							"vector": [0, 15, 0]
						},
						"3.0": {
							"vector": [0, -30, 0]
						},
						"4.0": {
							"vector": [0, 15, 0]
						}
					}
				},
				"right_leg": {
					"rotation": {
						"0.0": {
							"vector": [0, 15, 0]
						},
						"0.5": {
							"vector": [-31.17402, -8.53858, -0.03761]
						},
						"1.5": {
							"vector": [-0.39134, 7.15381, -0.01254]
						},
						"2.0": {
							"vector": [0, 15, 0]
						},
						"2.5": {
							"vector": [0, 15, 0]
						},
						"3.0": {
							"vector": [-12.5, 32.5, 0]
						},
						"4.0": {
							"vector": [0, 15, 0]
						}
					}
				},
				"left_leg": {
					"rotation": {
						"0.0": {
							"vector": [0, -22.5, 0]
						},
						"1.0": {
							"vector": [12.03444, -21.97545, -5.37228]
						},
						"1.5": {
							"vector": [-24.34905, -9.8019, -1.36679]
						},
						"2.0": {
							"vector": [-12.5, -20, 0]
						},
						"2.5": {
							"vector": [-14.28919, -9.30537, 0.52326]
						},
						"3.0": {
							"vector": [-6.59757, 0.39086, -1.9332]
						},
						"4.0": {
							"vector": [0, -22.5, 0]
						}
					}
				},
				"right_arm": {
					"rotation": {
						"0.0": {
							"vector": [20.14383, 31.36549, -75.91853]
						},
						"2.0": {
							"vector": [20.14383, 31.36549, -75.91853]
						}
					}
				},
				"right_arm2": {
					"rotation": {
						"0.0": {
							"vector": [23.97769, -8.0508, -82.41686]
						},
						"2.0": {
							"vector": [23.97769, -8.0508, -82.41686]
						}
					}
				},
				"left_arm": {
					"rotation": {
						"0.0": {
							"vector": [89.09044, 19.98015, 87.33978]
						},
						"2.0": {
							"vector": [89.09044, 19.98015, 87.33978]
						}
					}
				},
				"left_arm2": {
					"rotation": {
						"0.0": {
							"vector": [15, 0, 0]
						},
						"2.0": {
							"vector": [15, 0, 0]
						}
					}
				},
				"left_sword": {
					"rotation": {
						"0.0": {
							"vector": [0, 0, -22.5]
						},
						"2.0": {
							"vector": [0, 0, -22.5]
						}
					}
				},
				"head": {
					"rotation": {
						"0.0": {
							"vector": [17.5, 0, 0]
						},
						"2.0": {
							"vector": [17.5, 0, 0]
						}
					}
				},
				"fllag1": {
					"rotation": {
						"0.0": {
							"vector": [0, 0, 0]
						},
						"1.0": {
							"vector": [-2.46207, 0.43399, 9.99067]
						},
						"2.0": {
							"vector": [-2.4905, 0.21782, 4.99527]
						},
						"3.0": {
							"vector": [-2.5, 0, 0]
						},
						"4.0": {
							"vector": [0, 0, 0]
						}
					}
				},
				"flag2": {
					"rotation": {
						"0.0": {
							"vector": [0, 0, 0]
						},
						"1.0": {
							"vector": [-2.47864, -0.32621, -7.49294]
						},
						"2.0": {
							"vector": [-2.47864, -0.32621, -7.49294]
						},
						"3.0": {
							"vector": [-2.4905, -0.21782, -4.99527]
						},
						"4.0": {
							"vector": [0, 0, 0]
						}
					}
				},
				"flagflag": {
					"rotation": {
						"0.0": {
							"vector": [2.5, 0, 0]
						},
						"1.0": {
							"vector": [10, 0, 0]
						},
						"2.0": {
							"vector": [10, 0, 0]
						},
						"3.0": {
							"vector": [0, 0, 0]
						},
						"4.0": {
							"vector": [2.5, 0, 0]
						}
					}
				},
				"flagflag2": {
					"rotation": {
						"0.0": {
							"vector": [0, 0, 0]
						},
						"1.0": {
							"vector": [10, 0, 0]
						},
						"2.0": {
							"vector": [10, 0, 0]
						},
						"3.0": {
							"vector": [10, 0, 0]
						},
						"4.0": {
							"vector": [0, 0, 0]
						}
					}
				},
				"right_leg2": {
					"rotation": {
						"0.0": {
							"vector": [0, 0, 0]
						},
						"0.5": {
							"vector": [35, 0, 0]
						},
						"1.5": {
							"vector": [9.17, 0, 0]
						},
						"2.0": {
							"vector": [0, 0, 0]
						},
						"2.5": {
							"vector": [0, 0, 0]
						},
						"3.0": {
							"vector": [7.5, 0, 0]
						},
						"4.0": {
							"vector": [0, 0, 0]
						}
					}
				},
				"left_leg2": {
					"rotation": {
						"0.0": {
							"vector": [0, 0, 0]
						},
						"1.0": {
							"vector": [-0.33, 0, 0]
						},
						"1.5": {
							"vector": [44.5, 0, 0]
						},
						"2.0": {
							"vector": [6, 0, 0]
						},
						"2.5": {
							"vector": [17.5, 0, 0]
						},
						"4.0": {
							"vector": [0, 0, 0]
						}
					}
				}
			}
		},
		"animation.idle": {
			"loop": true,
			"animation_length": 2,
			"bones": {
				"main": {
					"rotation": {
						"0.0": {
							"vector": [0, 7.5, 0]
						},
						"2.0": {
							"vector": [0, 7.5, 0]
						}
					}
				},
				"legs": {
					"rotation": {
						"0.0": {
							"vector": [0, 15, 0]
						},
						"2.0": {
							"vector": [0, 15, 0]
						}
					}
				},
				"right_leg": {
					"rotation": {
						"0.0": {
							"vector": [0, 15, 0]
						},
						"2.0": {
							"vector": [0, 15, 0]
						}
					}
				},
				"left_leg": {
					"rotation": {
						"0.0": {
							"vector": [0, -22.5, 0]
						},
						"2.0": {
							"vector": [0, -22.5, 0]
						}
					}
				},
				"right_arm": {
					"rotation": {
						"0.0": {
							"vector": [20.14383, 31.36549, -75.91853]
						},
						"2.0": {
							"vector": [20.14383, 31.36549, -75.91853]
						}
					}
				},
				"right_arm2": {
					"rotation": {
						"0.0": {
							"vector": [23.97769, -8.0508, -82.41686]
						},
						"2.0": {
							"vector": [23.97769, -8.0508, -82.41686]
						}
					}
				},
				"left_arm": {
					"rotation": {
						"0.0": {
							"vector": [89.09044, 19.98015, 87.33978]
						},
						"2.0": {
							"vector": [89.09044, 19.98015, 87.33978]
						}
					}
				},
				"left_arm2": {
					"rotation": {
						"0.0": {
							"vector": [15, 0, 0]
						},
						"2.0": {
							"vector": [15, 0, 0]
						}
					}
				},
				"left_sword": {
					"rotation": {
						"0.0": {
							"vector": [0, 0, -22.5]
						},
						"2.0": {
							"vector": [0, 0, -22.5]
						}
					}
				},
				"head": {
					"rotation": {
						"0.0": {
							"vector": [17.5, 0, 0]
						},
						"2.0": {
							"vector": [17.5, 0, 0]
						}
					}
				},
				"fllag1": {
					"rotation": {
						"0.0": {
							"vector": [0, 0, 0]
						},
						"1.0": {
							"vector": [-2.5, 0, 0]
						},
						"2.0": {
							"vector": [0, 0, 0]
						}
					}
				},
				"flag2": {
					"rotation": {
						"0.0": {
							"vector": [0, 0, 0]
						},
						"1.0": {
							"vector": [-2.5, 0, 0]
						},
						"2.0": {
							"vector": [0, 0, 0]
						}
					}
				},
				"flagflag": {
					"rotation": {
						"0.0": {
							"vector": [2.5, 0, 0]
						},
						"1.0": {
							"vector": [0, 0, 0]
						},
						"2.0": {
							"vector": [2.5, 0, 0]
						}
					}
				},
				"flagflag2": {
					"rotation": {
						"0.0": {
							"vector": [0, 0, 0]
						},
						"1.0": {
							"vector": [-2.5, 0, 0]
						},
						"2.0": {
							"vector": [0, 0, 0]
						}
					}
				}
			}
		},
		"animation.attackone": {
			"animation_length": 2,
			"bones": {
				"main": {
					"rotation": {
						"0.0": {
							"vector": [0, 7.5, 0]
						},
						"2.0": {
							"vector": [0, 7.5, 0]
						}
					}
				},
				"legs": {
					"rotation": {
						"0.0": {
							"vector": [0, 15, 0]
						},
						"2.0": {
							"vector": [0, 15, 0]
						}
					}
				},
				"right_leg": {
					"rotation": {
						"0.0": {
							"vector": [0, 15, 0]
						},
						"2.0": {
							"vector": [0, 15, 0]
						}
					}
				},
				"left_leg": {
					"rotation": {
						"0.0": {
							"vector": [0, -22.5, 0]
						},
						"2.0": {
							"vector": [0, -22.5, 0]
						}
					}
				},
				"right_arm": {
					"rotation": {
						"0.0": {
							"vector": [20.14383, 31.36549, -75.91853]
						},
						"0.25": {
							"vector": [20.14, 31.37, -75.92]
						},
						"0.3333": {
							"vector": [29.54143, 22.86868, -55.52442]
						},
						"0.4167": {
							"vector": [36.34047, -5.63622, -13.48082],
							"easing": "easeOutExpo"
						},
						"0.5833": {
							"vector": [2.15431, -38.83241, 56.91829],
							"easing": "easeOutExpo"
						},
						"2.0": {
							"vector": [20.14383, 31.36549, -75.91853]
						}
					}
				},
				"right_arm2": {
					"rotation": {
						"0.0": {
							"vector": [23.97769, -8.0508, -82.41686]
						},
						"0.4167": {
							"vector": [23.98, -8.05, -82.42],
							"easing": "easeOutQuart"
						},
						"0.6667": {
							"vector": [-37.52553, -9.39997, -7.47216],
							"easing": "easeOutQuart"
						},
						"1.4167": {
							"vector": [-37.52553, -9.39997, -7.47216],
							"easing": "easeOutQuart"
						},
						"2.0": {
							"vector": [23.97769, -8.0508, -82.41686]
						}
					}
				},
				"left_arm": {
					"rotation": {
						"0.0": {
							"vector": [89.09044, 19.98015, 87.33978]
						},
						"2.0": {
							"vector": [89.09044, 19.98015, 87.33978]
						}
					}
				},
				"left_arm2": {
					"rotation": {
						"0.0": {
							"vector": [15, 0, 0]
						},
						"2.0": {
							"vector": [15, 0, 0]
						}
					}
				},
				"left_sword": {
					"rotation": {
						"0.0": {
							"vector": [0, 0, -22.5]
						},
						"2.0": {
							"vector": [0, 0, -22.5]
						}
					}
				},
				"head": {
					"rotation": {
						"0.0": {
							"vector": [17.5, 0, 0]
						},
						"0.4167": {
							"vector": [16.40487, -11.73845, 4.25916]
						},
						"2.0": {
							"vector": [17.5, 0, 0]
						}
					}
				},
				"fllag1": {
					"rotation": {
						"0.0": {
							"vector": [0, 0, 0]
						},
						"2.0": {
							"vector": [0, 0, 0]
						}
					}
				},
				"flag2": {
					"rotation": {
						"0.0": {
							"vector": [0, 0, 0]
						},
						"2.0": {
							"vector": [0, 0, 0]
						}
					}
				},
				"flagflag": {
					"rotation": {
						"0.0": {
							"vector": [2.5, 0, 0]
						},
						"2.0": {
							"vector": [2.5, 0, 0]
						}
					}
				},
				"flagflag2": {
					"rotation": {
						"0.0": {
							"vector": [0, 0, 0]
						},
						"2.0": {
							"vector": [0, 0, 0]
						}
					}
				},
				"right_leg2": {
					"rotation": {
						"0.0": {
							"vector": [0, 0, 0]
						},
						"2.0": {
							"vector": [0, 0, 0]
						}
					}
				},
				"left_leg2": {
					"rotation": {
						"0.0": {
							"vector": [0, 0, 0]
						},
						"2.0": {
							"vector": [0, 0, 0]
						}
					}
				},
				"body": {
					"rotation": {
						"0.0": {
							"vector": [0, 0, 0]
						},
						"0.2083": {
							"vector": [0, -57.5, 0]
						},
						"1.0": {
							"vector": [0, -42.5, 0]
						},
						"2.0": {
							"vector": [0, 0, 0]
						}
					}
				},
				"right_sword": {
					"rotation": {
						"0.0": {
							"vector": [0, 0, 0]
						},
						"0.5": {
							"vector": [0, 0, 0]
						},
						"0.625": {
							"vector": [0, 0, 87.5]
						},
						"1.5": {
							"vector": [0, 0, 87.5]
						},
						"2.0": {
							"vector": [0, 0, 0]
						}
					}
				}
			}
		},
		"animation.attacktwo": {
			"animation_length": 2,
			"bones": {
				"main": {
					"rotation": {
						"0.0": {
							"vector": [0, 7.5, 0]
						},
						"0.3333": {
							"vector": [27.5, 42.5, 0],
							"easing": "easeInExpo"
						},
						"0.75": {
							"vector": [-13.53048, -5.95682, 6.93479],
							"easing": "easeInExpo"
						},
						"0.9167": {
							"vector": [-14.28149, -61.01294, 14.41729]
						},
						"1.2917": {
							"vector": [0, 7.5, 0]
						}
					},
					"position": {
						"0.0": {
							"vector": [0, 0, 0]
						},
						"0.3333": {
							"vector": [0, -6, 0],
							"easing": "easeInExpo"
						},
						"0.75": {
							"vector": [0, -3.75, 0],
							"easing": "easeInExpo"
						},
						"1.2917": {
							"vector": [0, 0, 0]
						}
					}
				},
				"legs": {
					"rotation": {
						"0.0": {
							"vector": [0, 15, 0]
						},
						"0.3333": {
							"vector": [-30, 15, 0],
							"easing": "easeInExpo"
						},
						"0.75": {
							"vector": [24.09997, 1.34216, -6.2814],
							"easing": "easeInExpo"
						},
						"0.9167": {
							"vector": [6.99967, 27.50716, -5.72361]
						},
						"1.2917": {
							"vector": [0, 15, 0]
						}
					}
				},
				"right_leg": {
					"rotation": {
						"0.0": {
							"vector": [0, 15, 0]
						},
						"0.3333": {
							"vector": [-18.00599, 20.22275, 14.76328],
							"easing": "easeInExpo"
						},
						"0.75": {
							"vector": [1.99401, 20.22275, 14.76328],
							"easing": "easeInExpo"
						},
						"0.9167": {
							"vector": [-8.32742, 21.60256, 6.87036]
						},
						"1.2917": {
							"vector": [0, 15, 0]
						}
					}
				},
				"left_leg": {
					"rotation": {
						"0.0": {
							"vector": [0, -22.5, 0]
						},
						"0.3333": {
							"vector": [-18.56412, -33.18385, -25.41571],
							"easing": "easeInExpo"
						},
						"0.75": {
							"vector": [-25.51145, -51.78256, -15.27834],
							"easing": "easeInExpo"
						},
						"1.2917": {
							"vector": [0, -22.5, 0]
						}
					}
				},
				"right_arm": {
					"rotation": {
						"0.0": {
							"vector": [20.14383, 31.36549, -75.91853]
						},
						"0.125": {
							"vector": [20.14, 31.37, -75.92]
						},
						"0.375": {
							"vector": [36.24854, 6.27955, -29.57204]
						},
						"0.5417": {
							"vector": [36.25, 6.28, -29.57]
						},
						"0.6667": {
							"vector": [10.46347, -29.78888, -40.32899],
							"easing": "easeInBack"
						},
						"0.7083": {
							"vector": [18.9575, -46.46768, -49.01249]
						},
						"0.75": {
							"vector": [72.64902, -82.08299, -148.97904]
						},
						"1.0": {
							"vector": [148.75204, -75.31875, -226.07579]
						},
						"1.1667": {
							"vector": [0.36392, -50.01334, -78.40052]
						},
						"1.2917": {
							"vector": [-47.83008, 16.82437, 26.76508]
						},
						"1.4583": {
							"vector": [17.16992, 16.82437, 26.76508]
						},
						"1.9583": {
							"vector": [20.14383, 31.36549, -75.91853],
							"easing": "easeInOutCubic"
						}
					}
				},
				"right_arm2": {
					"rotation": {
						"0.0": {
							"vector": [23.97769, -8.0508, -82.41686]
						},
						"0.125": {
							"vector": [23.98, -8.05, -82.42]
						},
						"0.2083": {
							"vector": [8.41676, -23.85967, -29.98798]
						},
						"0.5": {
							"vector": [-110.55381, -7.11303, -8.04417]
						},
						"0.7083": {
							"vector": [-60.55381, -7.11303, -8.04417]
						},
						"1.2917": {
							"vector": [21.28296, -13.8524, -68.31964]
						},
						"2.0": {
							"vector": [23.97769, -8.0508, -82.41686]
						}
					}
				},
				"left_arm": {
					"rotation": {
						"0.0": {
							"vector": [89.09044, 19.98015, 87.33978]
						},
						"1.2917": {
							"vector": [89.09044, 19.98015, 87.33978]
						}
					}
				},
				"left_arm2": {
					"rotation": {
						"0.0": {
							"vector": [15, 0, 0]
						},
						"1.2917": {
							"vector": [15, 0, 0]
						}
					}
				},
				"left_sword": {
					"rotation": {
						"0.0": {
							"vector": [0, 0, -22.5]
						},
						"1.2917": {
							"vector": [0, 0, -22.5]
						}
					}
				},
				"head": {
					"rotation": {
						"0.0": {
							"vector": [17.5, 0, 0]
						},
						"1.2917": {
							"vector": [17.5, 0, 0]
						}
					}
				},
				"fllag1": {
					"rotation": {
						"0.0": {
							"vector": [0, 0, 0]
						},
						"1.2917": {
							"vector": [0, 0, 0]
						}
					}
				},
				"flag2": {
					"rotation": {
						"0.0": {
							"vector": [0, 0, 0]
						},
						"1.2917": {
							"vector": [0, 0, 0]
						}
					}
				},
				"flagflag": {
					"rotation": {
						"0.0": {
							"vector": [2.5, 0, 0]
						},
						"1.2917": {
							"vector": [2.5, 0, 0]
						}
					}
				},
				"flagflag2": {
					"rotation": {
						"0.0": {
							"vector": [0, 0, 0]
						},
						"1.2917": {
							"vector": [0, 0, 0]
						}
					}
				},
				"right_leg2": {
					"rotation": {
						"0.0": {
							"vector": [0, 0, 0]
						},
						"0.3333": {
							"vector": [2.5, 0, 0],
							"easing": "easeInExpo"
						},
						"0.75": {
							"vector": [2.5, 0, 0],
							"easing": "easeInExpo"
						},
						"0.9167": {
							"vector": [37.46271, 0.86717, -4.92442]
						},
						"1.2917": {
							"vector": [0, 0, 0]
						}
					}
				},
				"left_leg2": {
					"rotation": {
						"0.0": {
							"vector": [0, 0, 0]
						},
						"0.3333": {
							"vector": [70, 0, 0],
							"easing": "easeInExpo"
						},
						"0.75": {
							"vector": [40, 0, 0],
							"easing": "easeInExpo"
						},
						"1.2917": {
							"vector": [0, 0, 0]
						}
					}
				},
				"body": {
					"rotation": {
						"0.0": {
							"vector": [0, 0, 0]
						},
						"1.2917": {
							"vector": [0, 0, 0]
						}
					},
					"position": {
						"0.0": {
							"vector": [0, 0, 0]
						},
						"1.2917": {
							"vector": [0, 0, 0]
						}
					}
				},
				"right_sword": {
					"rotation": {
						"0.0": {
							"vector": [0, 0, 0]
						},
						"0.1667": {
							"vector": [0, 0, 0]
						},
						"0.3333": {
							"vector": [0, 0, 62]
						},
						"0.375": {
							"vector": [0, 0, 97.5]
						},
						"0.7083": {
							"vector": [0, 0, 107.5]
						},
						"0.75": {
							"vector": [0, -27.5, 85]
						},
						"1.2917": {
							"vector": [0, 0, 0]
						},
						"2.0": {
							"vector": [0, 0, 0]
						}
					}
				}
			}
		}
	},
	"geckolib_format_version": 2
}